{
  "$schema": "https://json-schema.org/draft/2020-12/schema",
  "$id": "https://raw.githubusercontent.com/api-evangelist/workday-business-processes/refs/heads/main/json-schema/workday-business-processes-approval-request-schema.json",
  "title": "Approval Request",
  "description": "Request to approve an inbox item in a business process",
  "type": "object",
  "properties": {
    "comment": {
      "type": "string",
      "description": "Approval comment"
    },
    "approverId": {
      "type": "string",
      "description": "ID of the approving user"
    }
  },
  "required": [
    "approverId"
  ]
}